gcs_uploader.py
PyUpdater_GCS_Plugin-1.0.0.dist-info/METADATA
PyUpdater_GCS_Plugin-1.0.0.dist-info/WHEEL
PyUpdater_GCS_Plugin-1.0.0.dist-info/entry_points.txt
PyUpdater_GCS_Plugin-1.0.0.dist-info/license.txt
PyUpdater_GCS_Plugin-1.0.0.dist-info/top_level.txt
PyUpdater_GCS_Plugin-1.0.0.dist-info/RECORD
