Metadata-Version: 2.1
Name: PyUpdater-GCS-Plugin
Version: 1.0.0
Summary: GCS plugin for PyUpdater
Home-page: https://github.com/PlaidCloud/PyUpdater-gcs-Plugin
Author: Tartan Solutions
Author-email: charlie.laymon@tartansolutions.com
License: UNKNOWN
Platform: Any
License-File: license.txt
Requires-Dist: google-cloud-storage
